zipcodeignoresamethread/__init__.py
zipcodeignoresamethread/zipcode.db
zipcodeignoresamethread-0.1.0.dist-info/DESCRIPTION.rst
zipcodeignoresamethread-0.1.0.dist-info/METADATA
zipcodeignoresamethread-0.1.0.dist-info/RECORD
zipcodeignoresamethread-0.1.0.dist-info/WHEEL
zipcodeignoresamethread-0.1.0.dist-info/metadata.json
zipcodeignoresamethread-0.1.0.dist-info/top_level.txt
