Metadata-Version: 2.0
Name: zipcodeignoresamethread
Version: 0.1.0
Summary: A simple python package for dealing with  zip codes in python.
Home-page: https://github.com/darren-elation/zipcode-ignore-same-thread
Author: Darren Tan
Author-email: darren.tan@elationemr.com
License: MIT
Keywords: zip codes
Platform: UNKNOWN
Classifier: Development Status :: 5 - Production/Stable
Classifier: Intended Audience :: Developers
Classifier: Topic :: Software Development :: Build Tools
Classifier: License :: OSI Approved :: MIT License
Classifier: Programming Language :: Python :: 2
Classifier: Programming Language :: Python :: 2.6
Classifier: Programming Language :: Python :: 2.7
Classifier: Programming Language :: Python :: 3
Classifier: Programming Language :: Python :: 3.2
Classifier: Programming Language :: Python :: 3.3
Classifier: Programming Language :: Python :: 3.4
Requires-Dist: haversine
